django_pycharm/management/commands/install_pycharm_commands.py
django_pycharm/management/commands/runscript.py
django_pycharm-0.1.3.dist-info/LICENSE
django_pycharm-0.1.3.dist-info/WHEEL
django_pycharm-0.1.3.dist-info/METADATA
django_pycharm-0.1.3.dist-info/RECORD
