Metadata-Version: 2.1
Name: django-pycharm
Version: 0.1.3
Summary: App for Django to run any Python script within Django context
Home-page: https://github.com/nouseforacode/django-pycharm
License: MIT
Author: nouseforacode
Author-email: 10090277+nouseforacode@users.noreply.github.com
Requires-Python: >=3.7
Classifier: License :: OSI Approved :: MIT License
Classifier: Programming Language :: Python :: 3
Classifier: Programming Language :: Python :: 3.7
Classifier: Programming Language :: Python :: 3.8
Classifier: Programming Language :: Python :: 3.9
Requires-Dist: Django (>=3)
Requires-Dist: xmltodict (>=0.12)
Project-URL: Repository, https://github.com/nouseforacode/django-pycharm
